spatula/optimize.py
spatula/CMakeLists.txt
spatula/util.py
spatula/pgop.py
spatula/sph_harm.py
spatula/__init__.py
spatula/integrate.py
spatula/sphere-codes.npz
spatula/bond_order.py
spatula/representations.py
spatula/_spatula.cpython-314-darwin.so
spatula_analysis-0.1.1.dist-info/RECORD
spatula_analysis-0.1.1.dist-info/WHEEL
spatula_analysis-0.1.1.dist-info/METADATA
spatula_analysis-0.1.1.dist-info/licenses/LICENSE
