Metadata-Version: 2.4
Name: spatula-analysis
Version: 0.1.1
Summary: Point group symmetry analysis of local environments for point cloud data.
Keywords: order parameter,point groups,molecular simulations,symmetry,crystallography,condensed matter,soft matter
License-Expression: BSD-3-Clause
License-File: LICENSE
Classifier: Development Status :: 4 - Beta
Classifier: Natural Language :: English
Classifier: Programming Language :: Python :: 3
Classifier: Programming Language :: Python :: 3.10
Classifier: Programming Language :: Python :: 3.11
Classifier: Programming Language :: Python :: 3.12
Classifier: Programming Language :: Python :: 3.13
Classifier: Programming Language :: Python :: 3.14
Project-URL: Documentation, https://spatula.readthedocs.io
Project-URL: Download, https://pypi.org/project/spatula-analysis/
Project-URL: Source, https://github.com/glotzerlab/spatula
Project-URL: Issues, https://github.com/glotzerlab/spatula/issues
Requires-Python: >=3.10
Requires-Dist: numpy
Requires-Dist: freud-analysis!=3.2.0,>=3.0.0
Requires-Dist: scipy
Provides-Extra: test
Requires-Dist: pytest; extra == "test"
Requires-Dist: pytest-rerunfailures; extra == "test"
Requires-Dist: coxeter; extra == "test"
